{
	"configurations" : 
	[
		{
			"directories" : 
			[
				{
					"build" : ".",
					"minimumCMakeVersion" : 
					{
						"string" : "3.16"
					},
					"projectIndex" : 0,
					"source" : ".",
					"targetIndexes" : 
					[
						0
					]
				}
			],
			"name" : "Debug",
			"projects" : 
			[
				{
					"directoryIndexes" : 
					[
						0
					],
					"name" : "eight088",
					"targetIndexes" : 
					[
						0
					]
				}
			],
			"targets" : 
			[
				{
					"directoryIndex" : 0,
					"id" : "eight088::@6890427a1f51a3e7e1df",
					"jsonFile" : "target-eight088-Debug-320f29a4286904e81ad0.json",
					"name" : "eight088",
					"projectIndex" : 0
				}
			]
		}
	],
	"kind" : "codemodel",
	"paths" : 
	{
		"build" : "/home/m1cha1s/projects/C/eight088/build",
		"source" : "/home/m1cha1s/projects/C/eight088"
	},
	"version" : 
	{
		"major" : 2,
		"minor" : 0
	}
}
